ChromeFetcher/__init__.py
ChromeFetcher/chrome_fetcher.py
chromefetcher-2025.5.132001.dist-info/licenses/LICENSE
tests/__init__.py
tests/test_chrome_fetcher.py
chromefetcher-2025.5.132001.dist-info/METADATA
chromefetcher-2025.5.132001.dist-info/WHEEL
chromefetcher-2025.5.132001.dist-info/top_level.txt
chromefetcher-2025.5.132001.dist-info/RECORD
